micropython/__init__.py
micropython/py.typed
pybricks/__init__.py
pybricks/_common.py
pybricks/ev3dev/_speaker.py
pybricks/ev3devices.py
pybricks/hubs.py
pybricks/iodevices.py
pybricks/media/__init__.py
pybricks/media/ev3dev.py
pybricks/media/py.typed
pybricks/messaging.py
pybricks/nxtdevices.py
pybricks/parameters.py
pybricks/pupdevices.py
pybricks/py.typed
pybricks/robotics.py
pybricks/tools.py
uerrno/__init__.py
uerrno/py.typed
uio/__init__.py
uio/py.typed
ujson/__init__.py
umath/__init__.py
umath/py.typed
urandom/__init__.py
urandom/py.typed
uselect/__init__.py
uselect/py.typed
ustruct/__init__.py
usys/__init__.py
usys/py.typed
pybricks-3.6.0.dist-info/AUTHORS.md
pybricks-3.6.0.dist-info/LICENSE
pybricks-3.6.0.dist-info/METADATA
pybricks-3.6.0.dist-info/WHEEL
pybricks-3.6.0.dist-info/RECORD
