Metadata-Version: 2.3
Name: pybricks
Version: 3.6.0
Summary: Documentation and user-API stubs for Pybricks MicroPython
License: MIT
Author: The Pybricks Authors
Author-email: team@pybricks.com
Maintainer: Laurens Valk
Maintainer-email: laurens@pybricks.com
Requires-Python: >=3.8,<4.0
Classifier: License :: OSI Approved :: MIT License
Classifier: Programming Language :: Python :: 3
Classifier: Programming Language :: Python :: 3.8
Classifier: Programming Language :: Python :: 3.9
Classifier: Programming Language :: Python :: 3.10
Classifier: Programming Language :: Python :: 3.11
Classifier: Programming Language :: Python :: 3.12
Classifier: Programming Language :: Python :: 3.13
Classifier: Programming Language :: Python :: Implementation :: MicroPython
Project-URL: Documentation, https://docs.pybricks.com
Project-URL: Homepage, https://pybricks.com
Project-URL: Repository, https://github.com/pybricks/pybricks-api
